.travis.yml
AUTHORS
ChangeLog
LICENSE
MANIFEST.in
README.md
compilio.py
requirements.txt
setup.cfg
setup.py
compilio/__init__.py
compilio/cli.py
compilio/config.py
compilio/config.yml
compilio_cli.egg-info/PKG-INFO
compilio_cli.egg-info/SOURCES.txt
compilio_cli.egg-info/dependency_links.txt
compilio_cli.egg-info/entry_points.txt
compilio_cli.egg-info/pbr.json
compilio_cli.egg-info/requires.txt
compilio_cli.egg-info/top_level.txt