Metadata-Version: 1.1
Name: compilio-cli
Version: 0.1.3
Summary: CLI tool to interact with Compilio API
Home-page: https://github.com/compilio/compilio-cli
Author: Quentin de Longraye
Author-email: UNKNOWN
License: GPL
Platform: UNKNOWN
Classifier: Environment :: Console
Classifier: Intended Audience :: Developers
Classifier: Programming Language :: Python :: 3
